mididoctor/Come To My Window.mid
mididoctor/MIDI-Doctor-Artwork.png
mididoctor/MIDI-Doctor-Logo.png
mididoctor/MIDI.py
mididoctor/README.md
mididoctor/__init__.py
mididoctor/mididoctor.py
mididoctor-25.7.20.dist-info/licenses/LICENSE
mididoctor-25.7.20.dist-info/METADATA
mididoctor-25.7.20.dist-info/WHEEL
mididoctor-25.7.20.dist-info/top_level.txt
mididoctor-25.7.20.dist-info/RECORD
